[{"year": "2014", "semester": "spring", "instructor": "CHOW, R", "grade_id": 353853, "section_number": "1"}, {"year": "2016", "semester": "spring", "instructor": "DECLERCQ, C", "grade_id": 359047, "section_number": "001"}, {"year": "2012", "semester": "spring", "instructor": "CRYSLER, C", "grade_id": 366518, "section_number": "1"}, {"year": "2013", "semester": "spring", "instructor": "DAMLUJI, M", "grade_id": 371464, "section_number": "1"}, {"year": "2015", "semester": "spring", "instructor": "CHOW, R", "grade_id": 373329, "section_number": "1"}]