[{"semester": "fall", "instructor": "CHOY, G", "section_number": "1", "year": "2014", "grade_id": 349233}, {"semester": "spring", "instructor": "ALLEN, R", "section_number": "1", "year": "2010", "grade_id": 350806}, {"semester": "fall", "instructor": "CHOY, G", "section_number": "1", "year": "2016", "grade_id": 357665}, {"semester": "fall", "instructor": "CHOY, G", "section_number": "1", "year": "2011", "grade_id": 365370}, {"semester": "fall", "instructor": "CHOY, G", "section_number": "1", "year": "2012", "grade_id": 370232}, {"semester": "fall", "instructor": "CHOY, G", "section_number": "1", "year": "2013", "grade_id": 375920}]