[{"year": "2014", "semester": "fall", "instructor": "HAYNES, J", "grade_id": 349251, "section_number": "1"}, {"year": "2014", "semester": "fall", "instructor": "VACCARO, J", "grade_id": 349252, "section_number": "2"}, {"year": "2014", "semester": "fall", "instructor": "HAYNES, J", "grade_id": 349253, "section_number": "3"}, {"year": "2014", "semester": "spring", "instructor": "VACCARO, J", "grade_id": 354509, "section_number": "1"}, {"year": "2014", "semester": "spring", "instructor": "MCELROY, D", "grade_id": 354510, "section_number": "2"}, {"year": "2014", "semester": "spring", "instructor": "GOETZ, C", "grade_id": 354511, "section_number": "3"}, {"year": "2014", "semester": "spring", "instructor": "BESSETTE, E", "grade_id": 354512, "section_number": "4"}, {"year": "2016", "semester": "fall", "instructor": "VACCARO, J", "grade_id": 357792, "section_number": "1"}, {"year": "2016", "semester": "fall", "instructor": "CHEN, J", "grade_id": 357793, "section_number": "2"}, {"year": "2016", "semester": "fall", "instructor": "BAO, W", "grade_id": 357794, "section_number": "3"}, {"year": "2016", "semester": "spring", "instructor": "LI, C", "grade_id": 359709, "section_number": "001"}, {"year": "2016", "semester": "spring", "instructor": "GOETZ, C", "grade_id": 359710, "section_number": "002"}, {"year": "2016", "semester": "spring", "instructor": "PREDESCU, A", "grade_id": 359711, "section_number": "004"}, {"year": "2016", "semester": "spring", "instructor": "ALPERT, J", "grade_id": 359712, "section_number": "005"}, {"year": "2016", "semester": "spring", "instructor": "PRANOLO, J", "grade_id": 359713, "section_number": "007"}, {"year": "2015", "semester": "fall", "instructor": "VACCARO, J", "grade_id": 363784, "section_number": "1"}, {"year": "2015", "semester": "fall", "instructor": "AIRRIESS, H", "grade_id": 363785, "section_number": "2"}, {"year": "2015", "semester": "fall", "instructor": "BESSETTE, E", "grade_id": 363786, "section_number": "3"}, {"year": "2012", "semester": "spring", "instructor": "WHISSEL, K", "grade_id": 367189, "section_number": "1"}, {"year": "2012", "semester": "spring", "instructor": "HAYNES, J", "grade_id": 367190, "section_number": "2"}, {"year": "2012", "semester": "spring", "instructor": "WHISSEL, K", "grade_id": 367191, "section_number": "3"}, {"year": "2012", "semester": "spring", "instructor": "CARPENTER, E", "grade_id": 367192, "section_number": "5"}, {"year": "2012", "semester": "fall", "instructor": "CARPENTER, E", "grade_id": 370254, "section_number": "1"}, {"year": "2012", "semester": "fall", "instructor": "CARPENTER, E", "grade_id": 370255, "section_number": "2"}, {"year": "2013", "semester": "spring", "instructor": "CARPENTER, E", "grade_id": 372101, "section_number": "1"}, {"year": "2013", "semester": "spring", "instructor": "CARPENTER, E", "grade_id": 372102, "section_number": "2"}, {"year": "2013", "semester": "spring", "instructor": "PUNNAMKUZHYIL, A", "grade_id": 372103, "section_number": "4"}, {"year": "2013", "semester": "spring", "instructor": "WHISSEL, K", "grade_id": 372104, "section_number": "5"}, {"year": "2015", "semester": "spring", "instructor": "HAYNES, J", "grade_id": 374005, "section_number": "1"}, {"year": "2015", "semester": "spring", "instructor": "HAYNES, J", "grade_id": 374006, "section_number": "2"}, {"year": "2015", "semester": "spring", "instructor": "AIRRIESS, H", "grade_id": 374007, "section_number": "3"}, {"year": "2015", "semester": "spring", "instructor": "VACCARO, J", "grade_id": 374008, "section_number": "4"}, {"year": "2015", "semester": "spring", "instructor": "JACOBSON, L", "grade_id": 374009, "section_number": "5"}, {"year": "2015", "semester": "spring", "instructor": "PREDESCU, A", "grade_id": 374010, "section_number": "6"}, {"year": "2015", "semester": "spring", "instructor": "GOETZ, C", "grade_id": 374011, "section_number": "7"}]