{"A+": {"percent": 0.0, "percentile_low": 1.0, "numerator": 0, "percentile_high": 1.0}, "C-": {"percent": 0.05, "percentile_low": 0.11, "numerator": 1, "percentile_high": 0.16}, "subtitle": "Welsh and Arthurian Literature of the Middle Ages", "B-": {"percent": 0.05, "percentile_low": 0.21, "numerator": 1, "percentile_high": 0.26}, "B+": {"percent": 0.16, "percentile_low": 0.37, "numerator": 3, "percentile_high": 0.53}, "A-": {"percent": 0.05, "percentile_low": 0.53, "numerator": 1, "percentile_high": 0.58}, "course_letter": "B+", "section_gpa": 3.412, "title": "CELTIC 119A", "section_letter": "B+", "course_id": 1123, "denominator": 19, "course_gpa": 3.346, "D": {"percent": 0.0, "percentile_low": 0.11, "numerator": 0, "percentile_high": 0.11}, "C+": {"percent": 0.0, "percentile_low": 0.21, "numerator": 0, "percentile_high": 0.21}, "F": {"percent": 0.0, "percentile_low": 0.11, "numerator": 0, "percentile_high": 0.11}, "A": {"percent": 0.42, "percentile_low": 0.58, "numerator": 8, "percentile_high": 1.0}, "C": {"percent": 0.05, "percentile_low": 0.16, "numerator": 1, "percentile_high": 0.21}, "B": {"percent": 0.11, "percentile_low": 0.26, "numerator": 2, "percentile_high": 0.37}}