{"A+": {"percent": 0.08, "percentile_low": 0.92, "numerator": 1, "percentile_high": 1.0}, "C-": {"percent": 0.08, "percentile_low": 0.25, "numerator": 1, "percentile_high": 0.33}, "subtitle": "Introduction to Analysis", "B-": {"percent": 0.08, "percentile_low": 0.5, "numerator": 1, "percentile_high": 0.58}, "B+": {"percent": 0.08, "percentile_low": 0.58, "numerator": 1, "percentile_high": 0.67}, "A-": {"percent": 0.17, "percentile_low": 0.67, "numerator": 2, "percentile_high": 0.83}, "course_letter": "B", "section_gpa": 2.317, "title": "MATH 104", "section_letter": "C+", "course_id": 4478, "denominator": 12, "course_gpa": 2.888, "D": {"percent": 0.08, "percentile_low": 0.17, "numerator": 1, "percentile_high": 0.25}, "C+": {"percent": 0.0, "percentile_low": 0.5, "numerator": 0, "percentile_high": 0.5}, "F": {"percent": 0.17, "percentile_low": 0.0, "numerator": 2, "percentile_high": 0.17}, "A": {"percent": 0.08, "percentile_low": 0.83, "numerator": 1, "percentile_high": 0.92}, "C": {"percent": 0.17, "percentile_low": 0.33, "numerator": 2, "percentile_high": 0.5}, "B": {"percent": 0.0, "percentile_low": 0.58, "numerator": 0, "percentile_high": 0.58}}