{"A+": {"percent": 0.02, "percentile_low": 0.98, "numerator": 1, "percentile_high": 1.0}, "C-": {"percent": 0.0, "percentile_low": 0.04, "numerator": 0, "percentile_high": 0.04}, "subtitle": "Peace Theory: Approaches and Analyses", "B-": {"percent": 0.07, "percentile_low": 0.04, "numerator": 3, "percentile_high": 0.11}, "B+": {"percent": 0.13, "percentile_low": 0.22, "numerator": 6, "percentile_high": 0.36}, "A-": {"percent": 0.42, "percentile_low": 0.36, "numerator": 19, "percentile_high": 0.78}, "course_letter": "B+", "section_gpa": 3.404, "title": "PACS 100", "section_letter": "B+", "course_id": 5602, "denominator": 45, "course_gpa": 3.275, "D": {"percent": 0.0, "percentile_low": 0.04, "numerator": 0, "percentile_high": 0.04}, "C+": {"percent": 0.0, "percentile_low": 0.04, "numerator": 0, "percentile_high": 0.04}, "F": {"percent": 0.04, "percentile_low": 0.0, "numerator": 2, "percentile_high": 0.04}, "A": {"percent": 0.2, "percentile_low": 0.78, "numerator": 9, "percentile_high": 0.98}, "C": {"percent": 0.0, "percentile_low": 0.04, "numerator": 0, "percentile_high": 0.04}, "B": {"percent": 0.11, "percentile_low": 0.11, "numerator": 5, "percentile_high": 0.22}}