{"A+": {"percent": 0.07, "percentile_low": 0.93, "numerator": 1, "percentile_high": 1.0}, "C-": {"percent": 0.0, "percentile_low": 0.07, "numerator": 0, "percentile_high": 0.07}, "subtitle": "The Origins and Development of Buddhist Art in South Asia", "B-": {"percent": 0.0, "percentile_low": 0.07, "numerator": 0, "percentile_high": 0.07}, "B+": {"percent": 0.36, "percentile_low": 0.29, "numerator": 5, "percentile_high": 0.64}, "A-": {"percent": 0.14, "percentile_low": 0.64, "numerator": 2, "percentile_high": 0.79}, "course_letter": "B+", "section_gpa": 3.454, "title": "BUDDSTD 150", "section_letter": "B+", "course_id": 7531, "denominator": 14, "course_gpa": 3.454, "D": {"percent": 0.0, "percentile_low": 0.07, "numerator": 0, "percentile_high": 0.07}, "C+": {"percent": 0.0, "percentile_low": 0.07, "numerator": 0, "percentile_high": 0.07}, "F": {"percent": 0.0, "percentile_low": 0.07, "numerator": 0, "percentile_high": 0.07}, "A": {"percent": 0.14, "percentile_low": 0.79, "numerator": 2, "percentile_high": 0.93}, "C": {"percent": 0.0, "percentile_low": 0.07, "numerator": 0, "percentile_high": 0.07}, "B": {"percent": 0.21, "percentile_low": 0.07, "numerator": 3, "percentile_high": 0.29}}