{"A+": {"percent": 0.36, "percentile_low": 0.64, "numerator": 27, "percentile_high": 1.0}, "C-": {"percent": 0.0, "percentile_low": 0.0, "numerator": 0, "percentile_high": 0.0}, "subtitle": "Urban Design: City-Building and Place-Making", "B-": {"percent": 0.0, "percentile_low": 0.0, "numerator": 0, "percentile_high": 0.0}, "B+": {"percent": 0.05, "percentile_low": 0.0, "numerator": 4, "percentile_high": 0.05}, "A-": {"percent": 0.08, "percentile_low": 0.05, "numerator": 6, "percentile_high": 0.13}, "course_letter": "A-", "section_gpa": 3.939, "title": "CY PLAN 140", "section_letter": "A", "course_id": 1690, "denominator": 76, "course_gpa": 3.596, "D": {"percent": 0.0, "percentile_low": 0.0, "numerator": 0, "percentile_high": 0.0}, "C+": {"percent": 0.0, "percentile_low": 0.0, "numerator": 0, "percentile_high": 0.0}, "F": {"percent": 0.0, "percentile_low": 0.0, "numerator": 0, "percentile_high": 0.0}, "A": {"percent": 0.51, "percentile_low": 0.13, "numerator": 39, "percentile_high": 0.64}, "C": {"percent": 0.0, "percentile_low": 0.0, "numerator": 0, "percentile_high": 0.0}, "B": {"percent": 0.0, "percentile_low": 0.0, "numerator": 0, "percentile_high": 0.0}}