{"A+": {"percent": 0.0, "percentile_low": 1.0, "numerator": 0, "percentile_high": 1.0}, "C-": {"percent": 0.0, "percentile_low": 0.0, "numerator": 0, "percentile_high": 0.0}, "subtitle": "Self, Representation, and Nation", "B-": {"percent": 0.0, "percentile_low": 0.0, "numerator": 0, "percentile_high": 0.0}, "B+": {"percent": 0.0, "percentile_low": 0.05, "numerator": 0, "percentile_high": 0.05}, "A-": {"percent": 0.26, "percentile_low": 0.05, "numerator": 5, "percentile_high": 0.32}, "course_letter": "A-", "section_gpa": 3.868, "title": "S,SEASN R5A", "section_letter": "A", "course_id": 6567, "denominator": 19, "course_gpa": 3.682, "D": {"percent": 0.0, "percentile_low": 0.0, "numerator": 0, "percentile_high": 0.0}, "C+": {"percent": 0.0, "percentile_low": 0.0, "numerator": 0, "percentile_high": 0.0}, "F": {"percent": 0.0, "percentile_low": 0.0, "numerator": 0, "percentile_high": 0.0}, "A": {"percent": 0.68, "percentile_low": 0.32, "numerator": 13, "percentile_high": 1.0}, "C": {"percent": 0.0, "percentile_low": 0.0, "numerator": 0, "percentile_high": 0.0}, "B": {"percent": 0.05, "percentile_low": 0.0, "numerator": 1, "percentile_high": 0.05}}