{"C-": {"percentile_low": 0.03, "percent": 0.0, "numerator": 0, "percentile_high": 0.03}, "B-": {"percentile_low": 0.03, "percent": 0.0, "numerator": 0, "percentile_high": 0.03}, "B+": {"percentile_low": 0.03, "percent": 0.07, "numerator": 2, "percentile_high": 0.1}, "C+": {"percentile_low": 0.03, "percent": 0.0, "numerator": 0, "percentile_high": 0.03}, "course_gpa": 3.581, "C": {"percentile_low": 0.03, "percent": 0.0, "numerator": 0, "percentile_high": 0.03}, "A-": {"percentile_low": 0.1, "percent": 0.31, "numerator": 9, "percentile_high": 0.41}, "D": {"percentile_low": 0.03, "percent": 0.0, "numerator": 0, "percentile_high": 0.03}, "A+": {"percentile_low": 0.83, "percent": 0.17, "numerator": 5, "percentile_high": 1.0}, "B": {"percentile_low": 0.03, "percent": 0.0, "numerator": 0, "percentile_high": 0.03}, "A": {"percentile_low": 0.41, "percent": 0.41, "numerator": 12, "percentile_high": 0.83}, "section_gpa": 3.721, "course_letter": "A-", "title": "ASAMST R2A", "subtitle": "Reading and Composition", "F": {"percentile_low": 0.0, "percent": 0.03, "numerator": 1, "percentile_high": 0.03}, "denominator": 29, "course_id": 522, "section_letter": "A-"}