{"C-": {"percentile_low": 0.0, "percent": 0.0, "numerator": 0, "percentile_high": 0.0}, "B-": {"percentile_low": 0.0, "percent": 0.0, "numerator": 0, "percentile_high": 0.0}, "B+": {"percentile_low": 0.0, "percent": 0.0, "numerator": 0, "percentile_high": 0.0}, "C+": {"percentile_low": 0.0, "percent": 0.0, "numerator": 0, "percentile_high": 0.0}, "course_gpa": 3.844, "C": {"percentile_low": 0.0, "percent": 0.0, "numerator": 0, "percentile_high": 0.0}, "A-": {"percentile_low": 0.0, "percent": 0.1, "numerator": 3, "percentile_high": 0.1}, "D": {"percentile_low": 0.0, "percent": 0.0, "numerator": 0, "percentile_high": 0.0}, "A+": {"percentile_low": 0.77, "percent": 0.23, "numerator": 7, "percentile_high": 1.0}, "B": {"percentile_low": 0.0, "percent": 0.0, "numerator": 0, "percentile_high": 0.0}, "A": {"percentile_low": 0.1, "percent": 0.68, "numerator": 21, "percentile_high": 0.77}, "section_gpa": 3.971, "course_letter": "A-", "title": "ART 178", "subtitle": "Game Design Methods", "F": {"percentile_low": 0.0, "percent": 0.0, "numerator": 0, "percentile_high": 0.0}, "denominator": 31, "course_id": 508, "section_letter": "A"}