{"C-": {"percentile_low": 0.1, "percent": 0.0, "numerator": 0, "percentile_high": 0.1}, "B-": {"percentile_low": 0.14, "percent": 0.03, "numerator": 1, "percentile_high": 0.17}, "B+": {"percentile_low": 0.28, "percent": 0.0, "numerator": 0, "percentile_high": 0.28}, "C+": {"percentile_low": 0.14, "percent": 0.0, "numerator": 0, "percentile_high": 0.14}, "course_gpa": 3.712, "C": {"percentile_low": 0.1, "percent": 0.03, "numerator": 1, "percentile_high": 0.14}, "A-": {"percentile_low": 0.28, "percent": 0.14, "numerator": 4, "percentile_high": 0.41}, "D": {"percentile_low": 0.1, "percent": 0.0, "numerator": 0, "percentile_high": 0.1}, "A+": {"percentile_low": 0.83, "percent": 0.17, "numerator": 5, "percentile_high": 1.0}, "B": {"percentile_low": 0.17, "percent": 0.1, "numerator": 3, "percentile_high": 0.28}, "A": {"percentile_low": 0.41, "percent": 0.41, "numerator": 12, "percentile_high": 0.83}, "section_gpa": 3.712, "course_letter": "A-", "title": "HISTORY 100B", "subtitle": "Special Topics in European History", "F": {"percentile_low": 0.1, "percent": 0.0, "numerator": 0, "percentile_high": 0.1}, "denominator": 29, "course_id": 3564, "section_letter": "A-"}