{"C-": {"percentile_low": 0.06, "percent": 0.0, "numerator": 0, "percentile_high": 0.06}, "B-": {"percentile_low": 0.06, "percent": 0.06, "numerator": 1, "percentile_high": 0.12}, "B+": {"percentile_low": 0.47, "percent": 0.12, "numerator": 2, "percentile_high": 0.59}, "C+": {"percentile_low": 0.06, "percent": 0.0, "numerator": 0, "percentile_high": 0.06}, "course_gpa": 3.489, "C": {"percentile_low": 0.06, "percent": 0.0, "numerator": 0, "percentile_high": 0.06}, "A-": {"percentile_low": 0.59, "percent": 0.35, "numerator": 6, "percentile_high": 0.94}, "D": {"percentile_low": 0.06, "percent": 0.0, "numerator": 0, "percentile_high": 0.06}, "A+": {"percentile_low": 1.0, "percent": 0.0, "numerator": 0, "percentile_high": 1.0}, "B": {"percentile_low": 0.12, "percent": 0.35, "numerator": 6, "percentile_high": 0.47}, "A": {"percentile_low": 0.94, "percent": 0.06, "numerator": 1, "percentile_high": 1.0}, "section_gpa": 3.344, "course_letter": "B+", "title": "THEATER R1B", "subtitle": "Performance: Writing and Research", "F": {"percentile_low": 0.06, "percent": 0.0, "numerator": 0, "percentile_high": 0.06}, "denominator": 17, "course_id": 7145, "section_letter": "B+"}