{"C-": {"percentile_low": 0.0, "percent": 0.05, "numerator": 1, "percentile_high": 0.05}, "B-": {"percentile_low": 0.32, "percent": 0.0, "numerator": 0, "percentile_high": 0.32}, "B+": {"percentile_low": 0.36, "percent": 0.14, "numerator": 3, "percentile_high": 0.5}, "C+": {"percentile_low": 0.18, "percent": 0.14, "numerator": 3, "percentile_high": 0.32}, "course_gpa": 3.158, "C": {"percentile_low": 0.05, "percent": 0.14, "numerator": 3, "percentile_high": 0.18}, "A-": {"percentile_low": 0.5, "percent": 0.32, "numerator": 7, "percentile_high": 0.82}, "D": {"percentile_low": 0.0, "percent": 0.0, "numerator": 0, "percentile_high": 0.0}, "A+": {"percentile_low": 1.0, "percent": 0.0, "numerator": 0, "percentile_high": 1.0}, "B": {"percentile_low": 0.32, "percent": 0.05, "numerator": 1, "percentile_high": 0.36}, "A": {"percentile_low": 0.82, "percent": 0.18, "numerator": 4, "percentile_high": 1.0}, "section_gpa": 3.155, "course_letter": "B+", "title": "ISF 190", "subtitle": "Senior Thesis", "F": {"percentile_low": 0.0, "percent": 0.0, "numerator": 0, "percentile_high": 0.0}, "denominator": 22, "course_id": 4065, "section_letter": "B+"}