{"A+": {"percent": 0.03, "percentile_low": 0.97, "numerator": 3, "percentile_high": 1.0}, "C-": {"percent": 0.03, "percentile_low": 0.02, "numerator": 3, "percentile_high": 0.05}, "subtitle": "Introduction to Environmental Sciences", "B-": {"percent": 0.07, "percentile_low": 0.15, "numerator": 7, "percentile_high": 0.22}, "B+": {"percent": 0.15, "percentile_low": 0.34, "numerator": 16, "percentile_high": 0.5}, "A-": {"percent": 0.19, "percentile_low": 0.5, "numerator": 20, "percentile_high": 0.69}, "course_letter": "B+", "section_gpa": 3.289, "title": "ENV SCI 10", "section_letter": "B+", "course_id": 2732, "denominator": 105, "course_gpa": 3.22, "D": {"percent": 0.0, "percentile_low": 0.02, "numerator": 0, "percentile_high": 0.02}, "C+": {"percent": 0.05, "percentile_low": 0.1, "numerator": 5, "percentile_high": 0.15}, "F": {"percent": 0.02, "percentile_low": 0.0, "numerator": 2, "percentile_high": 0.02}, "A": {"percent": 0.29, "percentile_low": 0.69, "numerator": 30, "percentile_high": 0.97}, "C": {"percent": 0.06, "percentile_low": 0.05, "numerator": 6, "percentile_high": 0.1}, "B": {"percent": 0.12, "percentile_low": 0.22, "numerator": 13, "percentile_high": 0.34}}