{"C-": {"percentile_low": 0.04, "percent": 0.0, "numerator": 0, "percentile_high": 0.04}, "B-": {"percentile_low": 0.06, "percent": 0.04, "numerator": 6, "percentile_high": 0.1}, "B+": {"percentile_low": 0.18, "percent": 0.09, "numerator": 14, "percentile_high": 0.27}, "C+": {"percentile_low": 0.05, "percent": 0.01, "numerator": 2, "percentile_high": 0.06}, "course_gpa": 3.547, "C": {"percentile_low": 0.04, "percent": 0.01, "numerator": 1, "percentile_high": 0.05}, "A-": {"percentile_low": 0.27, "percent": 0.22, "numerator": 36, "percentile_high": 0.49}, "D": {"percentile_low": 0.04, "percent": 0.0, "numerator": 0, "percentile_high": 0.04}, "A+": {"percentile_low": 0.85, "percent": 0.15, "numerator": 25, "percentile_high": 1.0}, "B": {"percentile_low": 0.1, "percent": 0.09, "numerator": 14, "percentile_high": 0.18}, "A": {"percentile_low": 0.49, "percent": 0.36, "numerator": 59, "percentile_high": 0.85}, "section_gpa": 3.604, "course_letter": "A-", "title": "PSYCH 10", "subtitle": "Research and Data Analysis in Psychology", "F": {"percentile_low": 0.02, "percent": 0.02, "numerator": 4, "percentile_high": 0.04}, "denominator": 164, "course_id": 9075, "section_letter": "A-"}