{"A+": {"percent": 0.06, "percentile_low": 0.94, "numerator": 6, "percentile_high": 1.0}, "C-": {"percent": 0.0, "percentile_low": 0.04, "numerator": 0, "percentile_high": 0.04}, "subtitle": "Introduction to Public Policy Analysis", "B-": {"percent": 0.02, "percentile_low": 0.06, "numerator": 2, "percentile_high": 0.09}, "B+": {"percent": 0.34, "percentile_low": 0.25, "numerator": 32, "percentile_high": 0.59}, "A-": {"percent": 0.19, "percentile_low": 0.59, "numerator": 18, "percentile_high": 0.78}, "course_letter": "B+", "section_gpa": 3.452, "title": "PUB POL 101", "section_letter": "B+", "course_id": 6355, "denominator": 93, "course_gpa": 3.379, "D": {"percent": 0.0, "percentile_low": 0.04, "numerator": 0, "percentile_high": 0.04}, "C+": {"percent": 0.02, "percentile_low": 0.04, "numerator": 2, "percentile_high": 0.06}, "F": {"percent": 0.0, "percentile_low": 0.04, "numerator": 0, "percentile_high": 0.04}, "A": {"percent": 0.15, "percentile_low": 0.78, "numerator": 14, "percentile_high": 0.94}, "C": {"percent": 0.0, "percentile_low": 0.04, "numerator": 0, "percentile_high": 0.04}, "B": {"percent": 0.16, "percentile_low": 0.09, "numerator": 15, "percentile_high": 0.25}}