{"C-": {"percentile_low": 0.22, "percent": 0.0, "numerator": 0, "percentile_high": 0.22}, "B-": {"percentile_low": 0.27, "percent": 0.0, "numerator": 0, "percentile_high": 0.27}, "B+": {"percentile_low": 0.33, "percent": 0.02, "numerator": 1, "percentile_high": 0.35}, "C+": {"percentile_low": 0.24, "percent": 0.02, "numerator": 1, "percentile_high": 0.27}, "course_gpa": 3.682, "C": {"percentile_low": 0.22, "percent": 0.02, "numerator": 1, "percentile_high": 0.24}, "A-": {"percentile_low": 0.35, "percent": 0.02, "numerator": 1, "percentile_high": 0.37}, "D": {"percentile_low": 0.22, "percent": 0.0, "numerator": 0, "percentile_high": 0.22}, "A+": {"percentile_low": 1.0, "percent": 0.0, "numerator": 0, "percentile_high": 1.0}, "B": {"percentile_low": 0.27, "percent": 0.06, "numerator": 3, "percentile_high": 0.33}, "A": {"percentile_low": 0.37, "percent": 0.63, "numerator": 31, "percentile_high": 1.0}, "section_gpa": 3.797, "course_letter": "A-", "title": "MIL AFF 1", "subtitle": "Military Physical Fitness", "F": {"percentile_low": 0.22, "percent": 0.0, "numerator": 0, "percentile_high": 0.22}, "denominator": 49, "course_id": 4952, "section_letter": "A-"}