{"A+": {"percent": 0.0, "percentile_low": 1.0, "numerator": 0, "percentile_high": 1.0}, "C-": {"percent": 0.0, "percentile_low": 0.0, "numerator": 0, "percentile_high": 0.0}, "subtitle": "Public Health Microbiology Laboratory", "B-": {"percent": 0.13, "percentile_low": 0.0, "numerator": 2, "percentile_high": 0.13}, "B+": {"percent": 0.25, "percentile_low": 0.25, "numerator": 4, "percentile_high": 0.5}, "A-": {"percent": 0.19, "percentile_low": 0.5, "numerator": 3, "percentile_high": 0.69}, "course_letter": "B+", "section_gpa": 3.481, "title": "PB HLTH 162L", "section_letter": "B+", "course_id": 5654, "denominator": 16, "course_gpa": 3.18, "D": {"percent": 0.0, "percentile_low": 0.0, "numerator": 0, "percentile_high": 0.0}, "C+": {"percent": 0.0, "percentile_low": 0.0, "numerator": 0, "percentile_high": 0.0}, "F": {"percent": 0.0, "percentile_low": 0.0, "numerator": 0, "percentile_high": 0.0}, "A": {"percent": 0.31, "percentile_low": 0.69, "numerator": 5, "percentile_high": 1.0}, "C": {"percent": 0.0, "percentile_low": 0.0, "numerator": 0, "percentile_high": 0.0}, "B": {"percent": 0.13, "percentile_low": 0.13, "numerator": 2, "percentile_high": 0.25}}