{"A+": {"percent": 0.05, "percentile_low": 0.95, "numerator": 12, "percentile_high": 1.0}, "C-": {"percent": 0.0, "percentile_low": 0.01, "numerator": 0, "percentile_high": 0.01}, "subtitle": "African Music Ensemble", "B-": {"percent": 0.0, "percentile_low": 0.05, "numerator": 0, "percentile_high": 0.05}, "B+": {"percent": 0.0, "percentile_low": 0.06, "numerator": 0, "percentile_high": 0.06}, "A-": {"percent": 0.0, "percentile_low": 0.06, "numerator": 0, "percentile_high": 0.06}, "course_letter": "A", "section_gpa": 3.91, "title": "MUSIC 148", "section_letter": "A", "course_id": 5097, "denominator": 225, "course_gpa": 3.956, "D": {"percent": 0.0, "percentile_low": 0.01, "numerator": 0, "percentile_high": 0.01}, "C+": {"percent": 0.0, "percentile_low": 0.05, "numerator": 0, "percentile_high": 0.05}, "F": {"percent": 0.0, "percentile_low": 0.01, "numerator": 0, "percentile_high": 0.01}, "A": {"percent": 0.89, "percentile_low": 0.06, "numerator": 200, "percentile_high": 0.95}, "C": {"percent": 0.04, "percentile_low": 0.01, "numerator": 9, "percentile_high": 0.05}, "B": {"percent": 0.01, "percentile_low": 0.05, "numerator": 2, "percentile_high": 0.06}}