{"A+": {"percent": 0.02, "percentile_low": 0.98, "numerator": 1, "percentile_high": 1.0}, "C-": {"percent": 0.0, "percentile_low": 0.03, "numerator": 0, "percentile_high": 0.03}, "subtitle": "Entrepreneurship", "B-": {"percent": 0.02, "percentile_low": 0.03, "numerator": 1, "percentile_high": 0.05}, "B+": {"percent": 0.3, "percentile_low": 0.21, "numerator": 19, "percentile_high": 0.51}, "A-": {"percent": 0.29, "percentile_low": 0.51, "numerator": 18, "percentile_high": 0.79}, "course_letter": "A-", "section_gpa": 3.508, "title": "UGBA 195A", "section_letter": "A-", "course_id": 1079, "denominator": 63, "course_gpa": 3.522, "D": {"percent": 0.0, "percentile_low": 0.03, "numerator": 0, "percentile_high": 0.03}, "C+": {"percent": 0.0, "percentile_low": 0.03, "numerator": 0, "percentile_high": 0.03}, "F": {"percent": 0.0, "percentile_low": 0.03, "numerator": 0, "percentile_high": 0.03}, "A": {"percent": 0.19, "percentile_low": 0.79, "numerator": 12, "percentile_high": 0.98}, "C": {"percent": 0.0, "percentile_low": 0.03, "numerator": 0, "percentile_high": 0.03}, "B": {"percent": 0.16, "percentile_low": 0.05, "numerator": 10, "percentile_high": 0.21}}