{"C-": {"percentile_low": 0.19, "percent": 0.0, "numerator": 0, "percentile_high": 0.19}, "B-": {"percentile_low": 0.22, "percent": 0.05, "numerator": 3, "percentile_high": 0.27}, "B+": {"percentile_low": 0.39, "percent": 0.22, "numerator": 14, "percentile_high": 0.61}, "C+": {"percentile_low": 0.2, "percent": 0.02, "numerator": 1, "percentile_high": 0.22}, "course_gpa": 3.454, "C": {"percentile_low": 0.19, "percent": 0.02, "numerator": 1, "percentile_high": 0.2}, "A-": {"percentile_low": 0.61, "percent": 0.2, "numerator": 13, "percentile_high": 0.81}, "D": {"percentile_low": 0.19, "percent": 0.0, "numerator": 0, "percentile_high": 0.19}, "A+": {"percentile_low": 1.0, "percent": 0.0, "numerator": 0, "percentile_high": 1.0}, "B": {"percentile_low": 0.27, "percent": 0.13, "numerator": 8, "percentile_high": 0.39}, "A": {"percentile_low": 0.81, "percent": 0.19, "numerator": 12, "percentile_high": 1.0}, "section_gpa": 3.437, "course_letter": "B+", "title": "RELIGST 90A", "subtitle": "Introductory Topics in Religious Studies", "F": {"percentile_low": 0.19, "percent": 0.0, "numerator": 0, "percentile_high": 0.19}, "denominator": 64, "course_id": 6404, "section_letter": "B+"}