{"C-": {"percentile_low": 0.29, "percent": 0.01, "numerator": 1, "percentile_high": 0.3}, "B-": {"percentile_low": 0.39, "percent": 0.04, "numerator": 6, "percentile_high": 0.42}, "B+": {"percentile_low": 0.59, "percent": 0.13, "numerator": 20, "percentile_high": 0.71}, "C+": {"percentile_low": 0.36, "percent": 0.03, "numerator": 5, "percentile_high": 0.39}, "course_gpa": 3.242, "C": {"percentile_low": 0.3, "percent": 0.06, "numerator": 9, "percentile_high": 0.36}, "A-": {"percentile_low": 0.71, "percent": 0.01, "numerator": 2, "percentile_high": 0.72}, "D": {"percentile_low": 0.29, "percent": 0.0, "numerator": 0, "percentile_high": 0.29}, "A+": {"percentile_low": 1.0, "percent": 0.0, "numerator": 0, "percentile_high": 1.0}, "B": {"percentile_low": 0.42, "percent": 0.16, "numerator": 26, "percentile_high": 0.59}, "A": {"percentile_low": 0.72, "percent": 0.28, "numerator": 44, "percentile_high": 1.0}, "section_gpa": 3.259, "course_letter": "B+", "title": "L & S C30T", "subtitle": "Drugs and the Brain", "F": {"percentile_low": 0.28, "percent": 0.01, "numerator": 2, "percentile_high": 0.29}, "denominator": 160, "course_id": 4403, "section_letter": "B+"}