{"A+": {"percent": 0.02, "percentile_low": 0.98, "numerator": 1, "percentile_high": 1.0}, "C-": {"percent": 0.02, "percentile_low": 0.0, "numerator": 1, "percentile_high": 0.02}, "subtitle": "Ethical Leadership in Business", "B-": {"percent": 0.02, "percentile_low": 0.02, "numerator": 1, "percentile_high": 0.04}, "B+": {"percent": 0.29, "percentile_low": 0.06, "numerator": 15, "percentile_high": 0.35}, "A-": {"percent": 0.47, "percentile_low": 0.35, "numerator": 24, "percentile_high": 0.82}, "course_letter": "A-", "section_gpa": 3.563, "title": "UGBA 170", "section_letter": "A-", "course_id": 1062, "denominator": 51, "course_gpa": 3.558, "D": {"percent": 0.0, "percentile_low": 0.0, "numerator": 0, "percentile_high": 0.0}, "C+": {"percent": 0.0, "percentile_low": 0.02, "numerator": 0, "percentile_high": 0.02}, "F": {"percent": 0.0, "percentile_low": 0.0, "numerator": 0, "percentile_high": 0.0}, "A": {"percent": 0.16, "percentile_low": 0.82, "numerator": 8, "percentile_high": 0.98}, "C": {"percent": 0.0, "percentile_low": 0.02, "numerator": 0, "percentile_high": 0.02}, "B": {"percent": 0.02, "percentile_low": 0.04, "numerator": 1, "percentile_high": 0.06}}