{"C-": {"percentile_low": 0.03, "percent": 0.04, "numerator": 5, "percentile_high": 0.07}, "B-": {"percentile_low": 0.25, "percent": 0.14, "numerator": 16, "percentile_high": 0.39}, "B+": {"percentile_low": 0.5, "percent": 0.13, "numerator": 14, "percentile_high": 0.63}, "C+": {"percentile_low": 0.13, "percent": 0.12, "numerator": 13, "percentile_high": 0.25}, "course_gpa": 3.171, "C": {"percentile_low": 0.07, "percent": 0.06, "numerator": 7, "percentile_high": 0.13}, "A-": {"percentile_low": 0.63, "percent": 0.15, "numerator": 17, "percentile_high": 0.78}, "D": {"percentile_low": 0.02, "percent": 0.01, "numerator": 1, "percentile_high": 0.03}, "A+": {"percentile_low": 0.99, "percent": 0.01, "numerator": 1, "percentile_high": 1.0}, "B": {"percentile_low": 0.39, "percent": 0.11, "numerator": 12, "percentile_high": 0.5}, "A": {"percentile_low": 0.78, "percent": 0.21, "numerator": 24, "percentile_high": 0.99}, "section_gpa": 3.051, "course_letter": "B+", "title": "ECON 115", "subtitle": "The World Economy in the Twentieth Century", "F": {"percentile_low": 0.0, "percent": 0.02, "numerator": 2, "percentile_high": 0.02}, "denominator": 112, "course_id": 2027, "section_letter": "B"}