{"C-": {"percentile_low": 0.16, "percent": 0.01, "numerator": 1, "percentile_high": 0.16}, "B-": {"percentile_low": 0.17, "percent": 0.08, "numerator": 12, "percentile_high": 0.25}, "B+": {"percentile_low": 0.37, "percent": 0.17, "numerator": 25, "percentile_high": 0.54}, "C+": {"percentile_low": 0.17, "percent": 0.0, "numerator": 0, "percentile_high": 0.17}, "course_gpa": 3.604, "C": {"percentile_low": 0.16, "percent": 0.01, "numerator": 1, "percentile_high": 0.17}, "A-": {"percentile_low": 0.54, "percent": 0.22, "numerator": 33, "percentile_high": 0.76}, "D": {"percentile_low": 0.16, "percent": 0.0, "numerator": 0, "percentile_high": 0.16}, "A+": {"percentile_low": 0.92, "percent": 0.08, "numerator": 12, "percentile_high": 1.0}, "B": {"percentile_low": 0.25, "percent": 0.12, "numerator": 17, "percentile_high": 0.37}, "A": {"percentile_low": 0.76, "percent": 0.16, "numerator": 23, "percentile_high": 0.92}, "section_gpa": 3.481, "course_letter": "A-", "title": "ENV DES 100", "subtitle": "The City: Theories and Methods in Urban Studies", "F": {"percentile_low": 0.16, "percent": 0.0, "numerator": 0, "percentile_high": 0.16}, "denominator": 147, "course_id": 2714, "section_letter": "B+"}