{"C-": {"percentile_low": 0.0, "percent": 0.0, "numerator": 0, "percentile_high": 0.0}, "B-": {"percentile_low": 0.0, "percent": 0.04, "numerator": 1, "percentile_high": 0.04}, "B+": {"percentile_low": 0.04, "percent": 0.17, "numerator": 4, "percentile_high": 0.21}, "C+": {"percentile_low": 0.0, "percent": 0.0, "numerator": 0, "percentile_high": 0.0}, "course_gpa": 3.584, "C": {"percentile_low": 0.0, "percent": 0.0, "numerator": 0, "percentile_high": 0.0}, "A-": {"percentile_low": 0.21, "percent": 0.42, "numerator": 10, "percentile_high": 0.63}, "D": {"percentile_low": 0.0, "percent": 0.0, "numerator": 0, "percentile_high": 0.0}, "A+": {"percentile_low": 1.0, "percent": 0.0, "numerator": 0, "percentile_high": 1.0}, "B": {"percentile_low": 0.04, "percent": 0.0, "numerator": 0, "percentile_high": 0.04}, "A": {"percentile_low": 0.63, "percent": 0.38, "numerator": 9, "percentile_high": 1.0}, "section_gpa": 3.704, "course_letter": "A-", "title": "GPP 105", "subtitle": "The Ethics, Methods, and Pragmatics of Global Practice", "F": {"percentile_low": 0.0, "percent": 0.0, "numerator": 0, "percentile_high": 0.0}, "denominator": 24, "course_id": 3734, "section_letter": "A-"}