{"A+": {"percent": 0.18, "percentile_low": 0.82, "numerator": 2, "percentile_high": 1.0}, "C-": {"percent": 0.0, "percentile_low": 0.0, "numerator": 0, "percentile_high": 0.0}, "subtitle": "Intermediate Dynamics", "B-": {"percent": 0.0, "percentile_low": 0.0, "numerator": 0, "percentile_high": 0.0}, "B+": {"percent": 0.0, "percentile_low": 0.0, "numerator": 0, "percentile_high": 0.0}, "A-": {"percent": 0.27, "percentile_low": 0.0, "numerator": 3, "percentile_high": 0.27}, "course_letter": "B+", "section_gpa": 3.918, "title": "MEC ENG 175", "section_letter": "A", "course_id": 4823, "denominator": 11, "course_gpa": 3.204, "D": {"percent": 0.0, "percentile_low": 0.0, "numerator": 0, "percentile_high": 0.0}, "C+": {"percent": 0.0, "percentile_low": 0.0, "numerator": 0, "percentile_high": 0.0}, "F": {"percent": 0.0, "percentile_low": 0.0, "numerator": 0, "percentile_high": 0.0}, "A": {"percent": 0.55, "percentile_low": 0.27, "numerator": 6, "percentile_high": 0.82}, "C": {"percent": 0.0, "percentile_low": 0.0, "numerator": 0, "percentile_high": 0.0}, "B": {"percent": 0.0, "percentile_low": 0.0, "numerator": 0, "percentile_high": 0.0}}