{"C-": {"percentile_low": 0.0, "percent": 0.01, "numerator": 1, "percentile_high": 0.01}, "B-": {"percentile_low": 0.05, "percent": 0.08, "numerator": 11, "percentile_high": 0.13}, "B+": {"percentile_low": 0.45, "percent": 0.28, "numerator": 39, "percentile_high": 0.73}, "C+": {"percentile_low": 0.02, "percent": 0.03, "numerator": 4, "percentile_high": 0.05}, "course_gpa": 3.282, "C": {"percentile_low": 0.01, "percent": 0.01, "numerator": 2, "percentile_high": 0.02}, "A-": {"percentile_low": 0.73, "percent": 0.21, "numerator": 30, "percentile_high": 0.94}, "D": {"percentile_low": 0.0, "percent": 0.0, "numerator": 0, "percentile_high": 0.0}, "A+": {"percentile_low": 1.0, "percent": 0.0, "numerator": 0, "percentile_high": 1.0}, "B": {"percentile_low": 0.13, "percent": 0.32, "numerator": 45, "percentile_high": 0.45}, "A": {"percentile_low": 0.94, "percent": 0.06, "numerator": 8, "percentile_high": 1.0}, "section_gpa": 3.224, "course_letter": "B+", "title": "POL SCI 4", "subtitle": "Introduction to Political Theory", "F": {"percentile_low": 0.0, "percent": 0.0, "numerator": 0, "percentile_high": 0.0}, "denominator": 140, "course_id": 6067, "section_letter": "B+"}