{"A+": {"percent": 0.0, "percentile_low": 1.0, "numerator": 0, "percentile_high": 1.0}, "C-": {"percent": 0.0, "percentile_low": 0.02, "numerator": 0, "percentile_high": 0.02}, "subtitle": "Professional Communication", "B-": {"percent": 0.0, "percentile_low": 0.02, "numerator": 0, "percentile_high": 0.02}, "B+": {"percent": 0.04, "percentile_low": 0.08, "numerator": 2, "percentile_high": 0.13}, "A-": {"percent": 0.04, "percentile_low": 0.12, "numerator": 2, "percentile_high": 0.17}, "course_letter": "A", "section_gpa": 3.894, "title": "MEC ENG 191K", "section_letter": "A", "course_id": 4832, "denominator": 48, "course_gpa": 3.949, "D": {"percent": 0.0, "percentile_low": 0.02, "numerator": 0, "percentile_high": 0.02}, "C+": {"percent": 0.0, "percentile_low": 0.02, "numerator": 0, "percentile_high": 0.02}, "F": {"percent": 0.0, "percentile_low": 0.02, "numerator": 0, "percentile_high": 0.02}, "A": {"percent": 0.83, "percentile_low": 0.17, "numerator": 40, "percentile_high": 1.0}, "C": {"percent": 0.0, "percentile_low": 0.02, "numerator": 0, "percentile_high": 0.02}, "B": {"percent": 0.06, "percentile_low": 0.02, "numerator": 3, "percentile_high": 0.08}}