{"A+": {"percent": 0.22, "percentile_low": 0.78, "numerator": 7, "percentile_high": 1.0}, "C-": {"percent": 0.0, "percentile_low": 0.03, "numerator": 0, "percentile_high": 0.03}, "subtitle": "Water Resources and the Environment", "B-": {"percent": 0.03, "percentile_low": 0.09, "numerator": 1, "percentile_high": 0.13}, "B+": {"percent": 0.06, "percentile_low": 0.25, "numerator": 2, "percentile_high": 0.31}, "A-": {"percent": 0.16, "percentile_low": 0.31, "numerator": 5, "percentile_high": 0.47}, "course_letter": "B+", "section_gpa": 3.494, "title": "GEOG C135", "section_letter": "B+", "course_id": 8135, "denominator": 32, "course_gpa": 3.494, "D": {"percent": 0.0, "percentile_low": 0.03, "numerator": 0, "percentile_high": 0.03}, "C+": {"percent": 0.0, "percentile_low": 0.09, "numerator": 0, "percentile_high": 0.09}, "F": {"percent": 0.03, "percentile_low": 0.0, "numerator": 1, "percentile_high": 0.03}, "A": {"percent": 0.31, "percentile_low": 0.47, "numerator": 10, "percentile_high": 0.78}, "C": {"percent": 0.06, "percentile_low": 0.03, "numerator": 2, "percentile_high": 0.09}, "B": {"percent": 0.13, "percentile_low": 0.13, "numerator": 4, "percentile_high": 0.25}}