{"C-": {"percentile_low": 0.04, "percent": 0.0, "numerator": 0, "percentile_high": 0.04}, "B-": {"percentile_low": 0.04, "percent": 0.04, "numerator": 1, "percentile_high": 0.07}, "B+": {"percentile_low": 0.07, "percent": 0.14, "numerator": 4, "percentile_high": 0.21}, "C+": {"percentile_low": 0.04, "percent": 0.0, "numerator": 0, "percentile_high": 0.04}, "course_gpa": 3.563, "C": {"percentile_low": 0.04, "percent": 0.0, "numerator": 0, "percentile_high": 0.04}, "A-": {"percentile_low": 0.21, "percent": 0.36, "numerator": 10, "percentile_high": 0.57}, "D": {"percentile_low": 0.04, "percent": 0.0, "numerator": 0, "percentile_high": 0.04}, "A+": {"percentile_low": 1.0, "percent": 0.0, "numerator": 0, "percentile_high": 1.0}, "B": {"percentile_low": 0.07, "percent": 0.0, "numerator": 0, "percentile_high": 0.07}, "A": {"percentile_low": 0.57, "percent": 0.43, "numerator": 12, "percentile_high": 1.0}, "section_gpa": 3.604, "course_letter": "A-", "title": "RHETOR 114", "subtitle": "Rhetoric of New Media", "F": {"percentile_low": 0.0, "percent": 0.04, "numerator": 1, "percentile_high": 0.04}, "denominator": 28, "course_id": 6443, "section_letter": "A-"}