{"C-": {"percentile_low": 0.09, "percent": 0.0, "numerator": 0, "percentile_high": 0.09}, "B-": {"percentile_low": 0.09, "percent": 0.18, "numerator": 4, "percentile_high": 0.27}, "B+": {"percentile_low": 0.41, "percent": 0.09, "numerator": 2, "percentile_high": 0.5}, "C+": {"percentile_low": 0.09, "percent": 0.0, "numerator": 0, "percentile_high": 0.09}, "course_gpa": 3.777, "C": {"percentile_low": 0.09, "percent": 0.0, "numerator": 0, "percentile_high": 0.09}, "A-": {"percentile_low": 0.5, "percent": 0.14, "numerator": 3, "percentile_high": 0.64}, "D": {"percentile_low": 0.09, "percent": 0.0, "numerator": 0, "percentile_high": 0.09}, "A+": {"percentile_low": 1.0, "percent": 0.0, "numerator": 0, "percentile_high": 1.0}, "B": {"percentile_low": 0.27, "percent": 0.14, "numerator": 3, "percentile_high": 0.41}, "A": {"percentile_low": 0.64, "percent": 0.36, "numerator": 8, "percentile_high": 1.0}, "section_gpa": 3.475, "course_letter": "A-", "title": "THEATER 10", "subtitle": "Fundamentals of Acting I", "F": {"percentile_low": 0.09, "percent": 0.0, "numerator": 0, "percentile_high": 0.09}, "denominator": 22, "course_id": 7146, "section_letter": "B+"}