{"C-": {"percentile_low": 0.03, "percent": 0.04, "numerator": 4, "percentile_high": 0.06}, "B-": {"percentile_low": 0.13, "percent": 0.11, "numerator": 12, "percentile_high": 0.24}, "B+": {"percentile_low": 0.36, "percent": 0.04, "numerator": 5, "percentile_high": 0.4}, "C+": {"percentile_low": 0.13, "percent": 0.0, "numerator": 0, "percentile_high": 0.13}, "course_gpa": 3.163, "C": {"percentile_low": 0.06, "percent": 0.07, "numerator": 8, "percentile_high": 0.13}, "A-": {"percentile_low": 0.4, "percent": 0.12, "numerator": 14, "percentile_high": 0.53}, "D": {"percentile_low": 0.0, "percent": 0.03, "numerator": 3, "percentile_high": 0.03}, "A+": {"percentile_low": 0.75, "percent": 0.25, "numerator": 29, "percentile_high": 1.0}, "B": {"percentile_low": 0.24, "percent": 0.12, "numerator": 14, "percentile_high": 0.36}, "A": {"percentile_low": 0.53, "percent": 0.22, "numerator": 25, "percentile_high": 0.75}, "section_gpa": 3.373, "course_letter": "B+", "title": "INTEGBI 137", "subtitle": "Human Endocrinology", "F": {"percentile_low": 0.0, "percent": 0.0, "numerator": 0, "percentile_high": 0.0}, "denominator": 114, "course_id": 3951, "section_letter": "B+"}