{"A+": {"percent": 0.07, "percentile_low": 0.93, "numerator": 2, "percentile_high": 1.0}, "C-": {"percent": 0.0, "percentile_low": 0.04, "numerator": 0, "percentile_high": 0.04}, "subtitle": "Special Topics", "B-": {"percent": 0.11, "percentile_low": 0.19, "numerator": 3, "percentile_high": 0.3}, "B+": {"percent": 0.26, "percentile_low": 0.3, "numerator": 7, "percentile_high": 0.56}, "A-": {"percent": 0.19, "percentile_low": 0.56, "numerator": 5, "percentile_high": 0.74}, "course_letter": "A-", "section_gpa": 3.331, "title": "COMPSCI 194", "section_letter": "B+", "course_id": 2349, "denominator": 27, "course_gpa": 3.505, "D": {"percent": 0.0, "percentile_low": 0.04, "numerator": 0, "percentile_high": 0.04}, "C+": {"percent": 0.11, "percentile_low": 0.07, "numerator": 3, "percentile_high": 0.19}, "F": {"percent": 0.0, "percentile_low": 0.04, "numerator": 0, "percentile_high": 0.04}, "A": {"percent": 0.19, "percentile_low": 0.74, "numerator": 5, "percentile_high": 0.93}, "C": {"percent": 0.04, "percentile_low": 0.04, "numerator": 1, "percentile_high": 0.07}, "B": {"percent": 0.0, "percentile_low": 0.3, "numerator": 0, "percentile_high": 0.3}}