{"C-": {"percentile_low": 0.0, "percent": 0.0, "numerator": 0, "percentile_high": 0.0}, "B-": {"percentile_low": 0.0, "percent": 0.0, "numerator": 0, "percentile_high": 0.0}, "B+": {"percentile_low": 0.0, "percent": 0.12, "numerator": 2, "percentile_high": 0.12}, "C+": {"percentile_low": 0.0, "percent": 0.0, "numerator": 0, "percentile_high": 0.0}, "course_gpa": 3.846, "C": {"percentile_low": 0.0, "percent": 0.0, "numerator": 0, "percentile_high": 0.0}, "A-": {"percentile_low": 0.12, "percent": 0.18, "numerator": 3, "percentile_high": 0.29}, "D": {"percentile_low": 0.0, "percent": 0.0, "numerator": 0, "percentile_high": 0.0}, "A+": {"percentile_low": 0.94, "percent": 0.06, "numerator": 1, "percentile_high": 1.0}, "B": {"percentile_low": 0.0, "percent": 0.0, "numerator": 0, "percentile_high": 0.0}, "A": {"percentile_low": 0.29, "percent": 0.65, "numerator": 11, "percentile_high": 0.94}, "section_gpa": 3.865, "course_letter": "A-", "title": "NUSCTX 145", "subtitle": "Nutrition Education and Counseling", "F": {"percentile_low": 0.0, "percent": 0.0, "numerator": 0, "percentile_high": 0.0}, "denominator": 17, "course_id": 5476, "section_letter": "A"}