{"A+": {"percent": 0.02, "percentile_low": 0.98, "numerator": 6, "percentile_high": 1.0}, "C-": {"percent": 0.01, "percentile_low": 0.04, "numerator": 5, "percentile_high": 0.05}, "subtitle": "Introduction to Communication Networks", "B-": {"percent": 0.15, "percentile_low": 0.18, "numerator": 50, "percentile_high": 0.33}, "B+": {"percent": 0.2, "percentile_low": 0.48, "numerator": 67, "percentile_high": 0.68}, "A-": {"percent": 0.13, "percentile_low": 0.68, "numerator": 45, "percentile_high": 0.81}, "course_letter": "B+", "section_gpa": 3.141, "title": "EL ENG 122", "section_letter": "B", "course_id": 2415, "denominator": 341, "course_gpa": 3.156, "D": {"percent": 0.01, "percentile_low": 0.03, "numerator": 4, "percentile_high": 0.04}, "C+": {"percent": 0.07, "percentile_low": 0.11, "numerator": 23, "percentile_high": 0.18}, "F": {"percent": 0.0, "percentile_low": 0.02, "numerator": 1, "percentile_high": 0.03}, "A": {"percent": 0.17, "percentile_low": 0.81, "numerator": 58, "percentile_high": 0.98}, "C": {"percent": 0.06, "percentile_low": 0.05, "numerator": 20, "percentile_high": 0.11}, "B": {"percent": 0.16, "percentile_low": 0.33, "numerator": 54, "percentile_high": 0.48}}