[{"semester": "fall", "instructor": "KUBO, I", "section_number": "1", "year": "2014", "grade_id": 349184}, {"semester": "fall", "instructor": "KUBO, I", "section_number": "1", "year": "2008", "grade_id": 361208}, {"semester": "fall", "instructor": "KUBO, I", "section_number": "1", "year": "2011", "grade_id": 365321}, {"semester": "fall", "instructor": "KUBO, I", "section_number": "1", "year": "2009", "grade_id": 368697}, {"semester": "fall", "instructor": "KUBO, I", "section_number": "1", "year": "2012", "grade_id": 370177}, {"semester": "fall", "instructor": "KUBO, I", "section_number": "1", "year": "2013", "grade_id": 375864}, {"semester": "fall", "instructor": "KUBO, I", "section_number": "1", "year": "2010", "grade_id": 377418}]