[{"semester": "fall", "instructor": "WARREN, D", "section_number": "1", "year": "2016", "grade_id": 358417}, {"semester": "spring", "instructor": "WARREN, D", "section_number": "001", "year": "2016", "grade_id": 360310}, {"semester": "fall", "instructor": "WARREN, D", "section_number": "1", "year": "2008", "grade_id": 361662}, {"semester": "fall", "instructor": "WARREN, D", "section_number": "1", "year": "2011", "grade_id": 365966}, {"semester": "fall", "instructor": "WARREN, D", "section_number": "1", "year": "2009", "grade_id": 369170}, {"semester": "fall", "instructor": "WARREN, D", "section_number": "1", "year": "2012", "grade_id": 370865}, {"semester": "fall", "instructor": "WARREN, D", "section_number": "1", "year": "2013", "grade_id": 376562}]