[{"semester": "fall", "instructor": "BAUTISTA, D", "section_number": "1", "year": "2014", "grade_id": 349758}, {"semester": "fall", "instructor": "LISHKO, P", "section_number": "1", "year": "2016", "grade_id": 358285}, {"semester": "fall", "instructor": "BAUTISTA, D", "section_number": "1", "year": "2015", "grade_id": 364231}, {"semester": "fall", "instructor": "BAUTISTA, D", "section_number": "1", "year": "2012", "grade_id": 370735}, {"semester": "fall", "instructor": "BAUTISTA, D", "section_number": "1", "year": "2013", "grade_id": 376429}]